hoodlogger/__init__.py
hoodlogger/decorators.py
hoodlogger/hoodlogger.py
hoodlogger/hoodthreadlogger.py
hoodlogger-0.0.4.dist-info/LICENSE
hoodlogger-0.0.4.dist-info/METADATA
hoodlogger-0.0.4.dist-info/WHEEL
hoodlogger-0.0.4.dist-info/top_level.txt
hoodlogger-0.0.4.dist-info/RECORD
