Metadata-Version: 2.1
Name: hoodlogger
Version: 0.0.4
Summary: Hood Logger python package
Home-page: https://github.com/asafsemo/hood_python-hoodlogger
Author: Asaf Semo
Author-email: asafsemo@gmail.com
License: UNKNOWN
Platform: UNKNOWN
Classifier: Programming Language :: Python :: 3
Classifier: Programming Language :: Python :: 3.6
Classifier: Programming Language :: Python :: 3.7
Classifier: License :: OSI Approved :: GNU General Public License v2 or later (GPLv2+)
Classifier: Operating System :: OS Independent
Requires-Dist: numpy (>=1.17)
Requires-Dist: Flask (>=1.1)
